use_storage/__init__.py
use_storage/storage.py
use_storage/storage_version_his.py
use_storage/storage_version_his1.py
use_storage/storage_version_his10.py
use_storage/storage_version_his11.py
use_storage/storage_version_his12.py
use_storage/storage_version_his13.py
use_storage/storage_version_his14.py
use_storage/storage_version_his2.py
use_storage/storage_version_his3.py
use_storage/storage_version_his4.py
use_storage/storage_version_his5.py
use_storage/storage_version_his6.py
use_storage/storage_version_his7.py
use_storage/storage_version_his8.py
use_storage/storage_version_his9.py
use_storage-3.0.0.dist-info/LICENSE
use_storage-3.0.0.dist-info/METADATA
use_storage-3.0.0.dist-info/WHEEL
use_storage-3.0.0.dist-info/top_level.txt
use_storage-3.0.0.dist-info/RECORD
